booty/__init__.py
booty/__main__.py
booty/comm_thread.py
booty/framer.py
booty/hex.py
booty/processors.py
booty/util.py
booty/version.py
booty-0.3.0.dist-info/METADATA
booty-0.3.0.dist-info/WHEEL
booty-0.3.0.dist-info/entry_points.txt
booty-0.3.0.dist-info/license.txt
booty-0.3.0.dist-info/top_level.txt
booty-0.3.0.dist-info/RECORD
