Metadata-Version: 2.1
Name: booty
Version: 0.3.0
Summary: Bootloader application
Home-page: https://github.com/slightlynybbled/booty
Author: Jason R. Jones
Author-email: slightlynybbled@gmail.com
License: MIT
Keywords: bootloader pic24 dspic
Platform: UNKNOWN
Classifier: Development Status :: 3 - Alpha
Classifier: Programming Language :: Python :: 3
Classifier: Programming Language :: Python :: 3.5
Classifier: Programming Language :: Python :: 3.6
Classifier: Natural Language :: English
Requires-Dist: click (>=6.7)
Requires-Dist: intelhex (>=2.1)
Requires-Dist: pyserial (>=3.3)
